scend/__init__.py
scend/initialParams.py
scend/lossFunc.py
scend/optimize.py
scend/scend.py
scend/utiles.py
scend/version.py
scend-1.0.3.dist-info/LICENSE
scend-1.0.3.dist-info/METADATA
scend-1.0.3.dist-info/WHEEL
scend-1.0.3.dist-info/top_level.txt
scend-1.0.3.dist-info/RECORD
